.hgignore
.hgtags
LICENSE.txt
MANIFEST.in
run_all_tests.py
setup.cfg
setup.py
onyx/__init__.py
onyx.egg-info/PKG-INFO
onyx.egg-info/SOURCES.txt
onyx.egg-info/dependency_links.txt
onyx.egg-info/namespace_packages.txt
onyx.egg-info/not-zip-safe
onyx.egg-info/requires.txt
onyx.egg-info/top_level.txt
onyx/commod/__init__.py
onyx/commod/timeseries.py
onyx/commod/ufo_commod_asset.py
onyx/commod/ufo_commod_contract.py
onyx/commod/ufo_commod_forward.py
onyx/commod/ufo_commod_futures.py
onyx/commod/ufo_commod_nrby.py
onyx/commod/ufo_commod_swap.py
onyx/commod/test/__init__.py
onyx/commod/test/test_ufo_commod_futures.py
onyx/econometrics/__init__.py
onyx/econometrics/arma_functions.py
onyx/econometrics/garch_functions.py
onyx/econometrics/gbm_functions.py
onyx/econometrics/regression.py
onyx/econometrics/test/__init__.py
onyx/econometrics/test/test_gbm_functions.py
onyx/equity/__init__.py
onyx/equity/ufo_cash_dividend.py
onyx/equity/ufo_corporate_actions.py
onyx/equity/ufo_depositary_receipt.py
onyx/equity/ufo_equity_asset.py
onyx/equity/ufo_equity_cash.py
onyx/equity/ufo_equity_cfd.py
onyx/equity/ufo_equity_index.py
onyx/equity/ufo_equity_index_contract.py
onyx/equity/ufo_equity_index_futures.py
onyx/equity/ufo_equity_pair.py
onyx/equity/ufo_equity_vol_matrix.py
onyx/equity/test/__init__.py
onyx/equity/test/test_ufo_equity_asset.py
onyx/equity/test/test_ufo_equity_cash.py
onyx/equity/test/test_ufo_equity_cfd.py
onyx/equity/test/test_ufo_equity_index.py
onyx/equity/test/test_ufo_equity_index_contract.py
onyx/equity/test/test_ufo_equity_index_futures.py
onyx/equity/test/test_ufo_equity_pair.py
onyx/quantlib/__init__.py
onyx/quantlib/black_scholes.py
onyx/quantlib/gabillon_g2f.py
onyx/quantlib/montecarlo_pricers.py
onyx/quantlib/tree_pricers.py
onyx/quantlib/test/__init__.py
onyx/quantlib/test/test_black_scholes.py
onyx/quantlib/test/test_montecarlo_pricers.py
onyx/quantlib/test/test_tree_pricers.py
onyx/risk/__init__.py
onyx/risk/attributions.py
onyx/risk/decorators.py
onyx/risk/timeseries.py
onyx/risk/ufo_risk.py
onyx/risk/test/__init__.py
onyx/risk/test/test_ufo_risk.py
onyx/scheduler/__init__.py
onyx/scheduler/scheduling_fns.py
onyx/scheduler/scheduling_server.py
