Metadata-Version: 1.1
Name: onyx
Version: 0.8.10
Summary: Onyx is a ramework to develop integrated trading, position management, pricing and risk management platforms.
Home-page: https://bitbucket.org/sbraccia/onyx
Author: carlo sbraccia
Author-email: carlosbraccia@yahoo.co.uk
License: UNKNOWN
Platform: UNKNOWN
Classifier: Development Status :: 4 - Beta
Classifier: Environment :: Console
Classifier: Intended Audience :: Developers
Classifier: Intended Audience :: Financial and Insurance Industry
Classifier: License :: OSI Approved :: Apache Software License
Classifier: Natural Language :: English
Classifier: Operating System :: OS Independent
Classifier: Programming Language :: Python :: 3.4
Classifier: Topic :: Software Development :: Libraries :: Python Modules
Classifier: Topic :: Software Development :: Libraries :: Application Frameworks
